{"playerName":"Faiz","shopName":"Test Shop","started":true,"tutorialComplete":false,"money":1000,"level":1,"shop":[{"name":"Cash Register","description":"How are customers going to pay if you don't have one of these?","price":0,"canNPCInteract":false,"state":"default","image":"assets/cashregister.png","dimensions":[282,271],"position":[240,430],"shouldDraw":true,"canMove":false,"id":0,"flipped":0,"uuid":"87d4e470-906a-42b1-b227-8cafd7ff12a0"}],"shopWidth":2560,"unlockedItems":[true,false,false,false],"lastPlayed":1487720552533}
